sage_sdk/__init__.py
sage_sdk/client.py
sage_sdk/django.py
sage_sdk/exceptions.py
sage_sdk/fastapi.py
sage_sdk/flask.py
sage_sdk/types.py
roselabs_sage-0.1.2.dist-info/METADATA
roselabs_sage-0.1.2.dist-info/WHEEL
roselabs_sage-0.1.2.dist-info/RECORD
