Metadata-Version: 2.4
Name: roselabs-sage
Version: 0.1.2
Summary: Sage SDK for Python - Customer support ticketing made simple
Project-URL: Homepage, https://sage.roselabs.io
Project-URL: Documentation, https://docs.roselabs.io/sage/sdk/python
Project-URL: Repository, https://github.com/roselabs/sage-python
Author-email: Rose Labs <support@roselabs.io>
License-Expression: MIT
Keywords: customer-service,helpdesk,sage,support,ticketing
Classifier: Development Status :: 4 - Beta
Classifier: Intended Audience :: Developers
Classifier: License :: OSI Approved :: MIT License
Classifier: Programming Language :: Python :: 3
Classifier: Programming Language :: Python :: 3.9
Classifier: Programming Language :: Python :: 3.10
Classifier: Programming Language :: Python :: 3.11
Classifier: Programming Language :: Python :: 3.12
Classifier: Topic :: Software Development :: Libraries :: Python Modules
Requires-Python: >=3.9
Requires-Dist: httpx>=0.25.0
Provides-Extra: all
Requires-Dist: django>=3.2; extra == 'all'
Requires-Dist: flask>=2.0.0; extra == 'all'
Requires-Dist: starlette>=0.27.0; extra == 'all'
Provides-Extra: dev
Requires-Dist: mypy>=1.0.0; extra == 'dev'
Requires-Dist: pytest-asyncio>=0.21.0; extra == 'dev'
Requires-Dist: pytest>=7.0.0; extra == 'dev'
Requires-Dist: ruff>=0.1.0; extra == 'dev'
Provides-Extra: django
Requires-Dist: django>=3.2; extra == 'django'
Provides-Extra: fastapi
Requires-Dist: starlette>=0.27.0; extra == 'fastapi'
Provides-Extra: flask
Requires-Dist: flask>=2.0.0; extra == 'flask'
